odoo8_addon_event_phone-8.0.0.1.0.99.dev6-py2.7-nspkg.pth
odoo8_addon_event_phone-8.0.0.1.0.99.dev6.dist-info/METADATA
odoo8_addon_event_phone-8.0.0.1.0.99.dev6.dist-info/RECORD
odoo8_addon_event_phone-8.0.0.1.0.99.dev6.dist-info/WHEEL
odoo8_addon_event_phone-8.0.0.1.0.99.dev6.dist-info/namespace_packages.txt
odoo8_addon_event_phone-8.0.0.1.0.99.dev6.dist-info/top_level.txt
odoo_addons/event_phone/__init__.py
odoo_addons/event_phone/__openerp__.py
odoo_addons/event_phone/event_phone.py
odoo_addons/event_phone/event_view.xml
odoo_addons/event_phone/i18n/es.po
odoo_addons/event_phone/i18n/event_phone.pot
odoo_addons/event_phone/i18n/fr.po
odoo_addons/event_phone/i18n/sl.po
odoo_addons/event_phone/i18n/tr.po
odoo_addons/event_phone/i18n/zh_CN.po
odoo_addons/event_phone/security/ir.model.access.csv
odoo_addons/event_phone/static/description/icon.png
